kermout_strips_api/__init__.py
kermout_strips_api/plan.py
kermout_strips_api-0.0.4.dist-info/LICENSE
kermout_strips_api-0.0.4.dist-info/METADATA
kermout_strips_api-0.0.4.dist-info/WHEEL
kermout_strips_api-0.0.4.dist-info/top_level.txt
kermout_strips_api-0.0.4.dist-info/RECORD
