Metadata-Version: 2.1
Name: kermout-strips-api
Version: 0.0.4
Summary: Remotely interact with Kermout's Strips System
Home-page: https://github.com/RazerMoon/Kermout_Strips_API
Author: RazerMoon
Author-email: rasync@rasync.xyz
License: UNKNOWN
Project-URL: Documentation, https://github.com/RazerMoon/Kermout_Strips_API/wiki
Project-URL: Source Code, https://github.com/RazerMoon/Kermout_Strips_API
Platform: UNKNOWN
Classifier: Programming Language :: Python :: 3
Classifier: License :: OSI Approved :: MIT License
Classifier: Operating System :: OS Independent
Requires-Python: >=3.8
Requires-Dist: requests
Requires-Dist: bs4
Requires-Dist: prettytable
Requires-Dist: lxml
